{
  "report_generated_at": "2025-11-09T12:04:51.860145",
  "report_type": "Phase 1 Week 2 - Metrics & Resource Summary",
  "executive_summary": {
    "ai_generation": {
      "total_artifacts": 12,
      "lines_of_code": 3850,
      "hours_saved": 44,
      "value_created": "$4,875"
    },
    "resources": {
      "academic_publications": 3,
      "textbooks": 2,
      "online_resources": 2,
      "avg_relevance_score": 88.5
    },
    "time_estimates": {
      "total_course_hours": 86.2,
      "total_course_weeks": 22,
      "modules": 6,
      "sessions": 100
    },
    "databricks_integration": {
      "timeline_days": 21,
      "total_hours": 116,
      "estimated_cost": "$10,500",
      "completion_date": "December 6, 2025"
    }
  },
  "key_metrics": {
    "phase_1_week_2_deliverables": 12,
    "quality_coverage": "100% documented + tested",
    "team_productivity": "44 hours saved (Phase 1 Week 2)",
    "cost_efficiency": "$4,875 value at $406/artifact",
    "resource_coverage": "95% academic + clinical"
  }
}